<doctrine-mapping>
    <entity name="App\Api\Shared\Domain\Model\Team">
        <lifecycle-callbacks>
            <lifecycle-callback type="prePersist" method="lifecycleFileUpload" />
            <lifecycle-callback type="preUpdate" method="lifecycleFileUpload" />
            <lifecycle-callback type="prePersist" method="updateTimestamps" />
            <lifecycle-callback type="preUpdate" method="updateTimestamps" />
        </lifecycle-callbacks>
        <id name="id" type="integer">
            <generator strategy="AUTO" />
        </id>
        <field name="name" type="string" length="100" />
        <field name="fifaCode" type="string" length="3"/>
        <field name="iso2" type="string" length="2" />
        <field name="flag" type="string" length="255" />
        <field name="createdAt" type="datetime" />
        <field name="updatedAt" type="datetime" />
    </entity>
</doctrine-mapping>